ifctrano/__init__.py
ifctrano/base.py
ifctrano/bounding_box.py
ifctrano/building.py
ifctrano/construction.py
ifctrano/example/verification.ifc
ifctrano/exceptions.py
ifctrano/main.py
ifctrano/space_boundary.py
ifctrano/types.py
ifctrano/utils.py
ifctrano-0.11.0.dist-info/METADATA
ifctrano-0.11.0.dist-info/WHEEL
ifctrano-0.11.0.dist-info/entry_points.txt
ifctrano-0.11.0.dist-info/licenses/LICENSE
ifctrano-0.11.0.dist-info/RECORD
