Metadata-Version: 2.4
Name: ifctrano
Version: 0.11.0
Summary: Package for generating building energy simulation model from IFC
License: GPL V3
License-File: LICENSE
Keywords: BIM,IFC,energy simulation,modelica,building energy simulation,buildings,ideas
Author: Ando Andriamamonjy
Author-email: andoludovic.andriamamonjy@gmail.com
Requires-Python: >=3.10,<3.13
Classifier: License :: Other/Proprietary License
Classifier: Programming Language :: Python :: 3
Classifier: Programming Language :: Python :: 3.10
Classifier: Programming Language :: Python :: 3.11
Classifier: Programming Language :: Python :: 3.12
Requires-Dist: ifcopenshell (>=0.8.1.post1,<0.9.0)
Requires-Dist: open3d (>=0.19.0,<0.20.0)
Requires-Dist: shapely (>=2.0.7,<3.0.0)
Requires-Dist: trano (>=0.13.0,<0.14.0)
Requires-Dist: typer (>=0.19.2,<0.20.0)
Requires-Dist: vedo (>=2025.5.3,<2026.0.0)
Project-URL: Repository, https://github.com/andoludo/ifctrano
